basel/__init__.py
basel/client.py
basel/components/__init__.py
basel/components/classes.py
basel/components/components.py
basel/components/links.py
basel/components/modules.py
basel/components/nodes.py
basel/config.py
basel/dtos.py
basel/exporters.py
basel/loaders/__init__.py
basel/loaders/loaders.py
basel/loaders/modules.py
basel/main.py
basel/parsers/__init__.py
basel/parsers/parser.py
basel/parsers/python_parser.py
basel/reports/__init__.py
basel/reports/as_plane.py
basel/reports/formats.py
basel/reports/reporter.py
basel/reports/reports.py
basel/utils.py
basel-1.1.2.dist-info/LICENSE
basel-1.1.2.dist-info/METADATA
basel-1.1.2.dist-info/WHEEL
basel-1.1.2.dist-info/entry_points.txt
basel-1.1.2.dist-info/RECORD
