Metadata-Version: 2.1
Name: basel
Version: 1.1.2
Summary: Report Architecture Data
Keywords: report
Author: Iram Luis Morales Santos
Author-email: iramluism@gmail.com
Requires-Python: >=3.10,<4.0
Classifier: Programming Language :: Python :: 3
Classifier: Programming Language :: Python :: 3.10
Classifier: Programming Language :: Python :: 3.11
Classifier: Programming Language :: Python :: 3.12
Requires-Dist: plantuml (>=0.3.0,<0.4.0)
Requires-Dist: tabulate (>=0.9.0,<0.10.0)
